commitlint/__init__.py
commitlint/__version__.py
commitlint/cli.py
commitlint/config.py
commitlint/console.py
commitlint/constants.py
commitlint/exceptions.py
commitlint/git_helpers.py
commitlint/linter/__init__.py
commitlint/linter/_linter.py
commitlint/linter/utils.py
commitlint/linter/validators.py
commitlint/messages.py
commitlint-1.13.3.dist-info/METADATA
commitlint-1.13.3.dist-info/WHEEL
commitlint-1.13.3.dist-info/entry_points.txt
commitlint-1.13.3.dist-info/licenses/LICENSE
commitlint-1.13.3.dist-info/RECORD
