Metadata-Version: 2.4
Name: commitlint
Version: 1.13.3
Summary: commitlint is a pre-commit hook designed to lint your commit messages according to the Conventional Commits standard.
License: GPL-3.0
License-File: LICENSE
Keywords: commitlint,commit lint,python commitlint,conventional commit,conventional commit message,python commit,github actions,pre-commit
Author: Ajesh Sen Thapa
Author-email: aj3sshh@gmail.com
Requires-Python: >=3.10
Classifier: License :: OSI Approved :: GNU General Public License v3 (GPLv3)
Classifier: Operating System :: OS Independent
Classifier: Programming Language :: Python
Classifier: Programming Language :: Python :: 3
Classifier: Programming Language :: Python :: 3.10
Classifier: Programming Language :: Python :: 3.11
Classifier: Programming Language :: Python :: 3.12
Classifier: Programming Language :: Python :: 3.13
Classifier: Programming Language :: Python :: 3.14
Classifier: Programming Language :: Python :: 3 :: Only
Project-URL: Changelog, https://github.com/opensource-nepal/commitlint/blob/main/CHANGELOG.md
Project-URL: Homepage, https://github.com/opensource-nepal/commitlint
Project-URL: Issues, https://github.com/opensource-nepal/commitlint/issues
Project-URL: Repository, https://github.com/opensource-nepal/commitlint
